[
  {
    "id": "nw-001",
    "category": "linux-kernel",
    "subcategory": "networking",
    "difficulty": "초급",
    "type": "multiple-choice",
    "question": "리눅스 커널에서 네트워크 패킷 데이터를 저장하고 관리하는 핵심 자료구조는 무엇인가?",
    "options": [
      "net_device",
      "sk_buff",
      "sock",
      "netfilter"
    ],
    "answer": 1,
    "explanation": "sk_buff(socket buffer)는 리눅스 커널 네트워크 스택에서 패킷 데이터를 저장하고 조작하는 핵심 자료구조입니다. 패킷이 커널을 통과하는 동안 sk_buff 구조체가 패킷의 헤더, 데이터, 메타정보를 관리합니다."
  },
  {
    "id": "nw-002",
    "category": "linux-kernel",
    "subcategory": "networking",
    "difficulty": "초급",
    "type": "multiple-choice",
    "question": "리눅스에서 소켓을 생성할 때 사용하는 시스템 콜의 올바른 프로토타입은?",
    "options": [
      "int socket(int domain, int type, int protocol)",
      "int socket(int type, int domain)",
      "int socket(char *addr, int port)",
      "int socket(int family, int backlog)"
    ],
    "answer": 0,
    "explanation": "socket() 시스템 콜은 domain(주소 체계, 예: AF_INET), type(소켓 유형, 예: SOCK_STREAM), protocol(프로토콜, 보통 0) 세 가지 인자를 받습니다. 이 호출은 파일 디스크립터를 반환합니다."
  },
  {
    "id": "nw-003",
    "category": "linux-kernel",
    "subcategory": "networking",
    "difficulty": "초급",
    "type": "short-answer",
    "question": "리눅스 커널에서 네트워크 인터페이스(NIC)를 추상화하며, 인터페이스 이름, MAC 주소, MTU 등의 정보를 담는 핵심 구조체는 ___이다.",
    "blankAnswers": [["net_device", "struct net_device"]],
    "explanation": "net_device는 include/linux/netdevice.h에 정의되어 있으며, 물리적 또는 가상 네트워크 인터페이스를 나타내는 핵심 구조체입니다. alloc_netdev() 또는 alloc_etherdev()를 통해 할당하고 register_netdev()로 등록합니다."
  },
  {
    "id": "nw-004",
    "category": "linux-kernel",
    "subcategory": "networking",
    "difficulty": "초급",
    "type": "multiple-choice",
    "question": "리눅스 커널의 netfilter 프레임워크에서 패킷을 허용하는 판정(verdict)은?",
    "options": [
      "NF_DROP",
      "NF_ACCEPT",
      "NF_STOLEN",
      "NF_QUEUE"
    ],
    "answer": 1,
    "explanation": "NF_ACCEPT는 패킷이 정상적으로 네트워크 스택을 통과하도록 허용합니다. NF_DROP은 패킷을 폐기하고, NF_STOLEN은 모듈이 패킷을 가져가며, NF_QUEUE는 사용자 공간으로 패킷을 전달합니다."
  },
  {
    "id": "nw-005",
    "category": "linux-kernel",
    "subcategory": "networking",
    "difficulty": "초급",
    "type": "short-answer",
    "question": "NAPI는 높은 트래픽 상황에서 ___ 문제를 해결하기 위해 도입되었으며, 인터럽트를 비활성화하고 ___ 모드로 전환하여 패킷을 일괄 처리한다.",
    "blankAnswers": [["인터럽트 폭주", "interrupt storm"], ["폴링", "polling"]],
    "explanation": "NAPI는 패킷이 대량으로 도착할 때 매 패킷마다 인터럽트를 발생시키는 대신, 인터럽트를 비활성화하고 폴링 모드로 전환하여 패킷을 일괄 처리합니다. 이를 통해 높은 트래픽 환경에서 CPU 사용률을 크게 줄일 수 있습니다."
  },
  {
    "id": "nw-006",
    "category": "linux-kernel",
    "subcategory": "networking",
    "difficulty": "초급",
    "type": "code-fill",
    "question": "다음은 TCP 서버 소켓을 생성하고 바인딩하는 기본 코드입니다. 빈칸을 채우세요.",
    "codeTemplate": "int sockfd;\nstruct sockaddr_in addr;\n\nsockfd = socket(___, SOCK_STREAM, 0);\n\naddr.sin_family = AF_INET;\naddr.sin_port = htons(8080);\naddr.sin_addr.s_addr = INADDR_ANY;\n\n___(sockfd, (struct sockaddr *)&addr, sizeof(addr));",
    "codeLanguage": "c",
    "blankAnswers": [
      ["AF_INET"],
      ["bind"]
    ],
    "explanation": "TCP 서버 소켓 프로그래밍에서 socket() 호출 시 AF_INET(IPv4 주소 체계)과 SOCK_STREAM(TCP)을 지정합니다. 이후 bind()를 호출하여 소켓에 주소와 포트를 할당합니다."
  },
  {
    "id": "nw-007",
    "category": "linux-kernel",
    "subcategory": "networking",
    "difficulty": "초급",
    "type": "multiple-choice",
    "question": "리눅스 network namespace에 대한 설명으로 올바른 것은?",
    "options": [
      "네트워크 네임스페이스는 커널 모듈로만 생성할 수 있다",
      "각 네임스페이스는 독립적인 네트워크 스택(라우팅 테이블, iptables 규칙, 인터페이스 등)을 가진다",
      "네트워크 네임스페이스 간에는 통신이 불가능하다",
      "하나의 프로세스는 여러 네트워크 네임스페이스에 동시에 속할 수 있다"
    ],
    "answer": 1,
    "explanation": "각 network namespace는 자체 네트워크 인터페이스, 라우팅 테이블, iptables 규칙, 소켓 등 완전히 독립된 네트워크 스택을 가집니다. veth pair를 통해 네임스페이스 간 통신이 가능하며, ip netns 명령이나 clone() 시스템 콜로 생성할 수 있습니다."
  },
  {
    "id": "nw-008",
    "category": "linux-kernel",
    "subcategory": "networking",
    "difficulty": "초급",
    "type": "code-fill",
    "question": "다음은 raw socket을 생성하여 ICMP 패킷을 직접 수신하는 코드입니다. 빈칸을 채우세요.",
    "codeTemplate": "int sockfd;\n\nsockfd = socket(AF_INET, ___, IPPROTO_ICMP);\nif (sockfd < 0) {\n    perror(\"socket\");\n    return -1;\n}\n\nchar buffer[4096];\nstruct sockaddr_in src_addr;\nsocklen_t addrlen = sizeof(src_addr);\n\nint n = ___(sockfd, buffer, sizeof(buffer), 0,\n           (struct sockaddr *)&src_addr, &addrlen);",
    "codeLanguage": "c",
    "blankAnswers": [
      ["SOCK_RAW"],
      ["recvfrom"]
    ],
    "explanation": "SOCK_RAW 타입의 소켓은 프로토콜 헤더를 포함한 원시 패킷을 직접 송수신할 수 있습니다. IPPROTO_ICMP를 지정하면 ICMP 패킷만 수신하며, recvfrom()으로 발신자 주소와 함께 데이터를 읽습니다."
  },
  {
    "id": "nw-009",
    "category": "linux-kernel",
    "subcategory": "networking",
    "difficulty": "중급",
    "type": "short-answer",
    "question": "수신 패킷은 NIC 드라이버에서 ___ 폴링으로 sk_buff를 할당한 뒤, ___를 호출하여 프로토콜 핸들러로 전달하고, L3에서 ___가, L4에서 tcp_v4_rcv()가 처리하여 소켓 수신 큐에 도달한다.",
    "blankAnswers": [["NAPI"], ["netif_receive_skb", "netif_receive_skb()"], ["ip_rcv", "ip_rcv()"]],
    "explanation": "패킷 수신 경로: NIC 하드웨어 → DMA 전송 → 드라이버 인터럽트 → NAPI poll → napi_gro_receive()/netif_receive_skb() → L3 (ip_rcv → ip_rcv_finish → ip_local_deliver) → L4 (tcp_v4_rcv → tcp_v4_do_rcv) → 소켓 수신 큐. 이 경로는 softirq(NET_RX_SOFTIRQ) 컨텍스트에서 처리됩니다."
  },
  {
    "id": "nw-010",
    "category": "linux-kernel",
    "subcategory": "networking",
    "difficulty": "중급",
    "type": "multiple-choice",
    "question": "sk_buff 구조체에서 skb->data가 가리키는 위치를 이더넷 헤더에서 IP 헤더로 이동시키는 함수는?",
    "options": [
      "skb_push()",
      "skb_pull()",
      "skb_reserve()",
      "skb_put()"
    ],
    "answer": 1,
    "explanation": "skb_pull()은 data 포인터를 뒤로 이동시켜 앞쪽 헤더를 제거합니다. 이더넷 헤더를 건너뛰고 IP 헤더로 이동할 때 사용됩니다. 반대로 skb_push()는 data 포인터를 앞으로 이동시켜 새 헤더를 추가하고, skb_put()은 tail을 이동시켜 데이터 끝에 공간을 추가하며, skb_reserve()는 빈 버퍼에서 headroom을 확보합니다."
  },
  {
    "id": "nw-011",
    "category": "linux-kernel",
    "subcategory": "networking",
    "difficulty": "중급",
    "type": "code-fill",
    "question": "다음은 리눅스 커널 netfilter 훅을 등록하는 코드입니다. 빈칸을 채우세요.",
    "codeTemplate": "static unsigned int my_hook_fn(void *priv,\n    struct sk_buff *skb,\n    const struct nf_hook_state *state)\n{\n    struct iphdr *iph = ip_hdr(skb);\n    if (iph->protocol == IPPROTO_TCP)\n        return NF_DROP;\n    return ___;\n}\n\nstatic struct nf_hook_ops my_hook = {\n    .hook     = my_hook_fn,\n    .pf       = NFPROTO_IPV4,\n    .hooknum  = ___,\n    .priority = NF_IP_PRI_FIRST,\n};\n\nstatic int __init my_init(void)\n{\n    return nf_register_net_hook(&init_net, &my_hook);\n}",
    "codeLanguage": "c",
    "blankAnswers": [
      ["NF_ACCEPT"],
      ["NF_INET_PRE_ROUTING", "NF_INET_LOCAL_IN", "NF_INET_FORWARD", "NF_INET_LOCAL_OUT", "NF_INET_POST_ROUTING"]
    ],
    "explanation": "netfilter 훅 함수는 NF_ACCEPT(허용), NF_DROP(차단) 등의 verdict를 반환합니다. hooknum은 패킷 처리 경로상의 훅 포인트를 지정하며, NF_INET_PRE_ROUTING(라우팅 전), NF_INET_LOCAL_IN(로컬 입력), NF_INET_FORWARD(포워딩), NF_INET_LOCAL_OUT(로컬 출력), NF_INET_POST_ROUTING(라우팅 후) 중 하나를 선택합니다."
  },
  {
    "id": "nw-012",
    "category": "linux-kernel",
    "subcategory": "networking",
    "difficulty": "중급",
    "type": "short-answer",
    "question": "AF_NETLINK 소켓은 ___와 사용자 공간 간의 ___ 메커니즘으로, 라우팅 테이블 관리 등 커널 네트워크 서브시스템과 통신하는 데 사용된다.",
    "blankAnswers": [["커널", "kernel"], ["IPC", "프로세스 간 통신"]],
    "explanation": "AF_NETLINK은 NETLINK_ROUTE(라우팅), NETLINK_FIREWALL(방화벽), NETLINK_KOBJECT_UEVENT(디바이스 이벤트) 등 다양한 프로토콜 패밀리를 제공합니다. iproute2 도구(ip 명령)가 내부적으로 netlink 소켓을 사용하여 커널과 통신합니다. 양방향 비동기 통신과 멀티캐스트 그룹 구독이 가능합니다."
  },
  {
    "id": "nw-013",
    "category": "linux-kernel",
    "subcategory": "networking",
    "difficulty": "중급",
    "type": "multiple-choice",
    "question": "리눅스 커널의 traffic control(tc) 서브시스템에서 qdisc의 역할은?",
    "options": [
      "패킷의 암호화 및 복호화를 담당한다",
      "네트워크 인터페이스의 송신 큐에서 패킷 스케줄링 정책을 구현한다",
      "TCP 연결의 상태를 추적한다",
      "ARP 테이블을 관리한다"
    ],
    "answer": 1,
    "explanation": "qdisc(queueing discipline)는 네트워크 인터페이스의 송신 큐에서 패킷의 순서와 속도를 제어하는 스케줄링 알고리즘입니다. pfifo_fast(기본), HTB(계층적 토큰 버킷), TBF(토큰 버킷 필터), SFQ(확률적 공정 큐잉) 등 다양한 qdisc가 있습니다."
  },
  {
    "id": "nw-014",
    "category": "linux-kernel",
    "subcategory": "networking",
    "difficulty": "중급",
    "type": "short-answer",
    "question": "네트워크 브릿징은 ___(데이터 링크 레이어)에서 동작하며, ___ 주소를 기반으로 프레임을 포워딩한다. 루프 방지를 위해 ___를 지원한다.",
    "blankAnswers": [["L2", "Layer 2", "레이어 2"], ["MAC"], ["STP", "Spanning Tree Protocol"]],
    "explanation": "리눅스 bridge는 br_add_bridge()로 생성하고, br_add_if()로 인터페이스를 추가합니다. br_handle_frame()에서 수신 프레임을 처리하며, FDB(Forwarding Database)에서 MAC 주소를 학습합니다. STP(Spanning Tree Protocol)를 지원하여 루프를 방지하고, VLAN 필터링도 가능합니다."
  },
  {
    "id": "nw-015",
    "category": "linux-kernel",
    "subcategory": "networking",
    "difficulty": "중급",
    "type": "code-fill",
    "question": "다음은 커널 모듈에서 sk_buff를 할당하고 데이터를 추가하는 코드입니다. 빈칸을 채우세요.",
    "codeTemplate": "struct sk_buff *skb;\nunsigned char *data;\n\n/* 최대 1500바이트 데이터를 위한 sk_buff 할당 */\nskb = ___(1500, GFP_KERNEL);\nif (!skb)\n    return -ENOMEM;\n\n/* 이더넷 헤더를 위한 headroom 확보 */\nskb_reserve(skb, ETH_HLEN);\n\n/* 데이터 영역에 100바이트 공간 추가 */\ndata = ___(skb, 100);\nmemset(data, 0, 100);",
    "codeLanguage": "c",
    "blankAnswers": [
      ["alloc_skb"],
      ["skb_put"]
    ],
    "explanation": "alloc_skb()는 지정된 크기의 sk_buff를 할당합니다. skb_reserve()는 빈 버퍼에서 data/tail 포인터를 앞으로 이동시켜 프로토콜 헤더를 위한 headroom을 확보합니다. skb_put()은 tail 포인터를 뒤로 이동시켜 데이터 공간을 확장하고, 추가된 영역의 시작 포인터를 반환합니다."
  },
  {
    "id": "nw-016",
    "category": "linux-kernel",
    "subcategory": "networking",
    "difficulty": "중급",
    "type": "multiple-choice",
    "question": "ethtool 인터페이스를 통해 커널 네트워크 드라이버에서 지원하는 기능이 아닌 것은?",
    "options": [
      "링크 속도 및 듀플렉스 설정 조회/변경",
      "드라이버 정보 및 펌웨어 버전 조회",
      "프로세스의 CPU 친화도(affinity) 설정",
      "RX/TX 링 버퍼 크기 조회/변경"
    ],
    "answer": 2,
    "explanation": "ethtool은 네트워크 인터페이스의 하드웨어 및 드라이버 설정을 조회/변경하는 도구입니다. 링크 속도, 드라이버 정보, 링 버퍼 크기, 오프로드 설정, 통계 조회, 인터럽트 코얼레싱 설정 등을 지원합니다. CPU 친화도 설정은 taskset이나 cgroup으로 수행하며 ethtool의 기능이 아닙니다."
  },
  {
    "id": "nw-017",
    "category": "linux-kernel",
    "subcategory": "networking",
    "difficulty": "중급",
    "type": "short-answer",
    "question": "___는 라우팅 테이블의 커널 내부 표현으로, IPv4 경로 항목을 ___ 자료구조로 저장하며, 패킷의 목적지 IP에 대해 ___를 호출하여 nexthop 정보를 얻는다.",
    "blankAnswers": [["FIB", "Forwarding Information Base"], ["trie", "LC-trie", "트라이"], ["fib_lookup", "fib_lookup()"]],
    "explanation": "FIB는 ip route 명령으로 설정한 라우팅 규칙을 LC-trie(Level Compressed trie) 구조로 저장하여 빠른 최장 접두사 매칭(LPM)을 수행합니다. fib_lookup()은 목적지 주소에 대한 라우팅 결과(fib_result)를 반환하며, nexthop 게이트웨이와 출력 인터페이스 정보를 포함합니다."
  },
  {
    "id": "nw-018",
    "category": "linux-kernel",
    "subcategory": "networking",
    "difficulty": "고급",
    "type": "code-fill",
    "question": "다음은 XDP(eXpress Data Path) 프로그램의 기본 구조입니다. 특정 목적지 포트(80)의 TCP 패킷을 드롭하는 코드의 빈칸을 채우세요.",
    "codeTemplate": "SEC(\"xdp\")\nint xdp_filter(struct xdp_md *ctx)\n{\n    void *data = (void *)(long)ctx->data;\n    void *data_end = (void *)(long)ctx->data_end;\n\n    struct ethhdr *eth = data;\n    if ((void *)(eth + 1) > data_end)\n        return XDP_PASS;\n\n    if (eth->h_proto != htons(ETH_P_IP))\n        return XDP_PASS;\n\n    struct iphdr *iph = (void *)(eth + 1);\n    if ((void *)(iph + 1) > data_end)\n        return XDP_PASS;\n\n    if (iph->protocol != IPPROTO_TCP)\n        return XDP_PASS;\n\n    struct tcphdr *tcph = (void *)iph + (iph->ihl * 4);\n    if ((void *)(tcph + 1) > data_end)\n        return XDP_PASS;\n\n    if (tcph->dest == htons(80))\n        return ___;\n\n    return ___;\n}",
    "codeLanguage": "c",
    "blankAnswers": [
      ["XDP_DROP"],
      ["XDP_PASS"]
    ],
    "explanation": "XDP는 드라이버 레벨에서 패킷을 처리하는 고성능 패킷 처리 프레임워크입니다. XDP_DROP은 패킷을 즉시 폐기하고, XDP_PASS는 일반 네트워크 스택으로 전달합니다. XDP_TX는 같은 인터페이스로 패킷을 반송하고, XDP_REDIRECT는 다른 인터페이스로 리다이렉트합니다. 데이터 경계 검사(bounds check)는 eBPF 검증기(verifier)를 통과하기 위해 필수입니다."
  },
  {
    "id": "nw-019",
    "category": "linux-kernel",
    "subcategory": "networking",
    "difficulty": "고급",
    "type": "multiple-choice",
    "question": "리눅스 커널의 TCP 혼잡 제어(congestion control)에서 CUBIC 알고리즘의 특징으로 올바른 것은?",
    "options": [
      "RTT에 비례하여 윈도우 크기를 선형적으로 증가시킨다",
      "패킷 손실 시점의 윈도우 크기를 기준으로 3차 함수(cubic function)를 사용하여 윈도우를 조절한다",
      "항상 고정된 윈도우 크기를 유지한다",
      "수신 측의 버퍼 크기만을 기반으로 전송률을 결정한다"
    ],
    "answer": 1,
    "explanation": "CUBIC은 리눅스의 기본 TCP 혼잡 제어 알고리즘으로, 패킷 손실 시점의 윈도우 크기(Wmax)를 기준으로 3차 함수(cubic function)를 사용합니다. 이를 통해 Wmax 근처에서는 윈도우 증가를 느리게 하여 안정성을 확보하고, Wmax에서 멀 때는 빠르게 증가시켜 대역폭 활용도를 높입니다. RTT에 독립적인 특성이 있어 고대역폭 환경에 유리합니다."
  },
  {
    "id": "nw-020",
    "category": "linux-kernel",
    "subcategory": "networking",
    "difficulty": "고급",
    "type": "short-answer",
    "question": "___는 특정 프로토콜에 대한 패킷 핸들러를 커널에 등록하는 함수이다. ___ 구조체의 type 필드에 프로토콜 번호(예: ETH_P_IP)를, ___ 필드에 핸들러 함수 포인터를 지정한다.",
    "blankAnswers": [["dev_add_pack", "dev_add_pack()"], ["packet_type"], ["func"]],
    "explanation": "네트워크 패킷이 netif_receive_skb()에 도달하면, 커널은 이더넷 프레임의 프로토콜 필드를 확인하고 등록된 packet_type 핸들러를 호출합니다. 예를 들어 IPv4의 경우 ip_rcv()가 ETH_P_IP(0x0800)에 대한 핸들러로 등록되어 있습니다. ptype_base 해시 테이블과 ptype_all 리스트로 관리됩니다."
  },
  {
    "id": "nw-021",
    "category": "linux-kernel",
    "subcategory": "networking",
    "difficulty": "고급",
    "type": "code-fill",
    "question": "다음은 간단한 리눅스 네트워크 드라이버에서 net_device_ops를 설정하는 코드입니다. 빈칸을 채우세요.",
    "codeTemplate": "static int my_net_open(struct net_device *dev)\n{\n    netif_start_queue(dev);\n    return 0;\n}\n\nstatic int my_net_stop(struct net_device *dev)\n{\n    netif_stop_queue(dev);\n    return 0;\n}\n\nstatic netdev_tx_t my_net_xmit(struct sk_buff *skb,\n                                struct net_device *dev)\n{\n    /* 패킷 전송 처리 */\n    dev_kfree_skb(skb);\n    return NETDEV_TX_OK;\n}\n\nstatic const struct net_device_ops my_netdev_ops = {\n    .ndo_open       = ___,\n    .ndo_stop       = my_net_stop,\n    .ndo_start_xmit = ___,\n};",
    "codeLanguage": "c",
    "blankAnswers": [
      ["my_net_open"],
      ["my_net_xmit"]
    ],
    "explanation": "net_device_ops 구조체는 네트워크 디바이스의 주요 동작을 정의합니다. ndo_open은 ifconfig up 시 호출되어 인터페이스를 활성화하고, ndo_stop은 ifconfig down 시 호출됩니다. ndo_start_xmit은 패킷 전송 시 호출되는 핵심 함수로, sk_buff를 받아 하드웨어로 전송합니다. netif_start_queue()와 netif_stop_queue()는 커널의 패킷 전송 큐를 제어합니다."
  },
  {
    "id": "nw-022",
    "category": "linux-kernel",
    "subcategory": "networking",
    "difficulty": "고급",
    "type": "multiple-choice",
    "question": "nftables에서 사용하는 커널 내부 가상 머신(nf_tables)의 특징으로 올바르지 않은 것은?",
    "options": [
      "레지스터 기반의 가상 머신으로 패킷 매칭 규칙을 실행한다",
      "iptables와 달리 테이블, 체인, 규칙의 계층 구조를 사용자가 자유롭게 정의할 수 있다",
      "커널 모듈을 추가하지 않고도 새로운 프로토콜 매칭을 지원할 수 있다",
      "nftables는 iptables보다 항상 더 많은 시스템 콜을 필요로 한다"
    ],
    "answer": 3,
    "explanation": "nftables는 iptables보다 시스템 콜 사용이 효율적입니다. iptables는 규칙 추가/삭제마다 전체 규칙셋을 교체하는 반면, nftables는 nfnetlink 기반의 원자적 배치(batch) 업데이트를 지원합니다. nf_tables의 레지스터 기반 VM은 범용적이어서 별도의 커널 매치 모듈 없이도 다양한 프로토콜을 처리할 수 있습니다."
  },
  {
    "id": "nw-023",
    "category": "linux-kernel",
    "subcategory": "networking",
    "difficulty": "고급",
    "type": "short-answer",
    "question": "___는 수신 측에서 여러 작은 패킷을 하나로 병합(coalescing)하여 처리 횟수를 줄이고, ___는 송신 측에서 큰 패킷을 가능한 늦게 분할(segmentation)하여 스택 처리를 최소화한다.",
    "blankAnswers": [["GRO", "Generic Receive Offload"], ["GSO", "Generic Segmentation Offload"]],
    "explanation": "GRO는 napi_gro_receive()에서 동일한 플로우의 패킷들을 병합합니다. TCP의 경우 시퀀스 번호가 연속인 세그먼트를 하나의 큰 sk_buff로 합칩니다. GSO는 dev_queue_xmit() 경로에서 하드웨어가 지원하지 않는 경우에만 분할을 수행합니다. 두 기술 모두 소프트웨어 기반이므로 하드웨어 의존성이 없으며, per-packet 오버헤드를 크게 줄여 처리량을 향상시킵니다."
  },
  {
    "id": "nw-024",
    "category": "linux-kernel",
    "subcategory": "networking",
    "difficulty": "고급",
    "type": "code-fill",
    "question": "다음은 NAPI를 사용하는 네트워크 드라이버의 poll 함수 구현입니다. 빈칸을 채우세요.",
    "codeTemplate": "static int my_poll(struct napi_struct *napi, int budget)\n{\n    struct my_priv *priv = container_of(napi, struct my_priv, napi);\n    int work_done = 0;\n\n    while (work_done < budget) {\n        struct sk_buff *skb = my_rx_packet(priv);\n        if (!skb)\n            break;\n\n        skb->protocol = eth_type_trans(skb, priv->netdev);\n        napi_gro_receive(napi, skb);\n        work_done++;\n    }\n\n    if (work_done < budget) {\n        ___(napi, work_done);\n        /* 인터럽트 다시 활성화 */\n        my_enable_irq(priv);\n    }\n\n    return ___;\n}",
    "codeLanguage": "c",
    "blankAnswers": [
      ["napi_complete_done", "napi_complete"],
      ["work_done"]
    ],
    "explanation": "NAPI poll 함수는 budget만큼의 패킷을 처리합니다. 처리한 패킷 수가 budget보다 적으면 더 이상 처리할 패킷이 없다는 의미이므로, napi_complete_done()을 호출하여 폴링 모드를 종료하고 인터럽트를 다시 활성화합니다. work_done을 반환하여 커널에 실제 처리한 패킷 수를 알립니다. budget만큼 모두 처리했다면 커널이 다시 poll을 호출합니다."
  },
  {
    "id": "nw-025",
    "category": "linux-kernel",
    "subcategory": "networking",
    "difficulty": "고급",
    "type": "multiple-choice",
    "question": "eBPF 기반의 소켓 프로그램(BPF_PROG_TYPE_SOCK_OPS)이 TCP 연결에서 수행할 수 있는 작업이 아닌 것은?",
    "options": [
      "TCP 혼잡 제어 알고리즘을 연결별로 동적으로 변경",
      "TCP 연결의 RTT 정보를 수집하여 맵에 저장",
      "SYN 패킷 수신 시 커널의 TCP 3-way handshake를 완전히 우회",
      "TCP 소켓 옵션(예: TCP_NODELAY)을 BPF 프로그램에서 설정"
    ],
    "answer": 2,
    "explanation": "BPF_PROG_TYPE_SOCK_OPS는 TCP 이벤트(연결 설정, 상태 변경, RTT 측정 등)에 훅을 걸어 동작을 커스터마이즈할 수 있지만, TCP 3-way handshake 자체를 우회하는 것은 불가능합니다. SYN cookie와 같은 메커니즘은 별도의 XDP/TC 프로그램(BPF_PROG_TYPE_XDP)으로 처리할 수 있으나, 완전한 핸드셰이크 우회는 TCP 프로토콜의 근본적인 동작을 위반하므로 지원되지 않습니다."
  }
]
